{
  "configType": "FIELD",
  "description": "Represent a BRIGHTLowerFloorsTotalBedrooms field",
  "systemName": "BRIGHTLowerFloorsTotalBedrooms_LowerLevelsTotalBedrooms",
  "displayName": "BRIGHTLowerFloorsTotalBedrooms",
  "shortName": null,
  "standardName": null,
  "id": 200017266959,
  "availableFlag": 1,
  "dataTypeId": 10000000145,
  "visibleFlag": true,
  "nullableFlag": true,
  "pickListId": null,
  "displayOrder": null,
  "updatableFlag": true,
  "enterableFlag": true,
  "copyOnCloneFlag": true,
  "isDeprecated": false
}