{
  "configType": "FIELD",
  "description": "Represent a CWALandLeaseFlag field",
  "systemName": "CWALandLeaseFlag_EXISTS_FLAG",
  "displayName": "CWA_FIE_INCOME_EXPENSE_TYPES_LAND_LEASE_F_XSTS_FLG",
  "shortName": null,
  "standardName": null,
  "id": 200005004131,
  "availableFlag": 1,
  "dataTypeId": 10000000136,
  "visibleFlag": true,
  "nullableFlag": true,
  "pickListId": null,
  "displayOrder": null,
  "updatableFlag": true,
  "enterableFlag": true,
  "copyOnCloneFlag": true,
  "isDeprecated": false
}