{
  "configType": "FIELD",
  "description": "Represent a BRIGHTMobileHomeType field",
  "systemName": "BRIGHTMobileHomeType_BodyType",
  "displayName": "BRIGHTMobileHomeType",
  "shortName": null,
  "standardName": "BodyType",
  "id": 200017264462,
  "availableFlag": 1,
  "dataTypeId": 200017260569,
  "visibleFlag": true,
  "nullableFlag": true,
  "pickListId": 50070517919,
  "displayOrder": null,
  "updatableFlag": true,
  "enterableFlag": true,
  "copyOnCloneFlag": true,
  "isDeprecated": false
}