{
  "configType": "FIELD",
  "description": "Represent a CWALocationType field",
  "systemName": "CWALocationType_QSO_LOCATION_TYPE",
  "displayName": "CWA_LIS_QSO_LOCATION_TYPE",
  "shortName": null,
  "standardName": null,
  "id": 200005004330,
  "availableFlag": 1,
  "dataTypeId": 200004437394,
  "visibleFlag": true,
  "nullableFlag": true,
  "pickListId": 10000001425,
  "displayOrder": null,
  "updatableFlag": true,
  "enterableFlag": true,
  "copyOnCloneFlag": true,
  "isDeprecated": false
}