{
  "configType": "FIELD",
  "description": "Represent a BRIGHTDomProperty field",
  "systemName": "BRIGHTDomProperty_CumulativeDaysOnMarket",
  "displayName": "BRIGHTDomProperty",
  "shortName": null,
  "standardName": "CumulativeDaysOnMarket",
  "id": 200017265398,
  "availableFlag": 1,
  "dataTypeId": 200004272321,
  "visibleFlag": true,
  "nullableFlag": true,
  "pickListId": null,
  "displayOrder": null,
  "updatableFlag": true,
  "enterableFlag": true,
  "copyOnCloneFlag": true,
  "isDeprecated": false
}