{
  "configType": "FIELD",
  "description": "Represent a BRIGHTStreetNameAndSuffix field",
  "systemName": "BRIGHTStreetNameAndSuffix_StreetNameAndSuffix",
  "displayName": "BRIGHTStreetNameAndSuffix",
  "shortName": null,
  "standardName": null,
  "id": 200017268269,
  "availableFlag": 1,
  "dataTypeId": 10000000128,
  "visibleFlag": true,
  "nullableFlag": true,
  "pickListId": null,
  "displayOrder": null,
  "updatableFlag": true,
  "enterableFlag": true,
  "copyOnCloneFlag": true,
  "isDeprecated": false
}