{
  "configType": "FIELD",
  "description": "Represent a CWAListOfficePrimaryAssociationLkp field",
  "systemName": "CWAListOfficePrimaryAssociationLkp_QSO_PRIMARY_ASSOCIATION",
  "displayName": "SYS_CWLAGORG1_QSO_PRIMARY_ASSOCIATION",
  "shortName": null,
  "standardName": null,
  "id": 200005003888,
  "availableFlag": 1,
  "dataTypeId": 10000070536,
  "visibleFlag": true,
  "nullableFlag": true,
  "pickListId": 85004730491,
  "displayOrder": null,
  "updatableFlag": true,
  "enterableFlag": true,
  "copyOnCloneFlag": true,
  "isDeprecated": false
}