{
  "configType": "FIELD",
  "description": "Represent a AgentOtherPhone1 field",
  "systemName": "AgentOtherPhone1_CM_PHONE_NUMBER",
  "displayName": "SYS_PCPVW_PHONE_TYPES_OTHER_1_CM",
  "shortName": null,
  "standardName": "MemberOtherPhoneTeamNumber",
  "id": 50001041250,
  "availableFlag": 1,
  "dataTypeId": 10000000160,
  "visibleFlag": true,
  "nullableFlag": true,
  "pickListId": null,
  "displayOrder": null,
  "updatableFlag": false,
  "enterableFlag": false,
  "copyOnCloneFlag": false,
  "isDeprecated": false
}