{
  "configType": "FIELD",
  "description": "Represent a SourceModificationTimestamp field",
  "systemName": "SourceModificationTimestamp_QSDT_SOURCE_MODIFICATION_TMS",
  "displayName": "LIS_LIS_QSDT_SOURCE_MODIFICATION",
  "shortName": null,
  "standardName": null,
  "id": 50000911854,
  "availableFlag": 1,
  "dataTypeId": 50000898056,
  "visibleFlag": true,
  "nullableFlag": true,
  "pickListId": null,
  "displayOrder": null,
  "updatableFlag": true,
  "enterableFlag": true,
  "copyOnCloneFlag": true,
  "isDeprecated": false
}