{
  "configType": "FIELD",
  "description": "Represent a AgentDisplayStreetNumber field",
  "systemName": "AgentDisplayStreetNumber_ADDR_DISPLAY_HOUSE_NUMBER",
  "displayName": "SYS_PCAVW_ADDRESS_TYPES_HOME_1_A",
  "shortName": null,
  "standardName": null,
  "id": 50001055371,
  "availableFlag": 1,
  "dataTypeId": 10000000133,
  "visibleFlag": true,
  "nullableFlag": true,
  "pickListId": null,
  "displayOrder": null,
  "updatableFlag": true,
  "enterableFlag": true,
  "copyOnCloneFlag": true,
  "isDeprecated": false
}