{
  "configType": "FIELD",
  "description": "Represent a AgentPreferredFirstName field",
  "systemName": "AgentPreferredFirstName_QSS_PREFERRED_FIRST_NAME",
  "displayName": "SYS_PER_QSS_PREFERRED_FIRST_NAME",
  "shortName": null,
  "standardName": null,
  "id": 50000914928,
  "availableFlag": 1,
  "dataTypeId": 200007752035,
  "visibleFlag": true,
  "nullableFlag": true,
  "pickListId": null,
  "displayOrder": null,
  "updatableFlag": true,
  "enterableFlag": true,
  "copyOnCloneFlag": true,
  "isDeprecated": false
}