{
  "configType": "FIELD",
  "description": "Represent a Unit1BedroomMaster1Description field",
  "systemName": "Unit1BedroomMaster1Description_QMO_UNIT_FEATURES",
  "displayName": "LIS_ROOM_SUB_RM_TYPS_NT_1_BDRM_M",
  "shortName": null,
  "standardName": null,
  "id": 50038765338,
  "availableFlag": 1,
  "dataTypeId": 10000081633,
  "visibleFlag": true,
  "nullableFlag": true,
  "pickListId": 50038643744,
  "displayOrder": null,
  "updatableFlag": true,
  "enterableFlag": true,
  "copyOnCloneFlag": true,
  "isDeprecated": false
}