{
  "configType": "FIELD",
  "description": "Represent a RenewalCompensations field",
  "systemName": "RenewalCompensations_QMO_RENEWAL_COMPENSATIONS",
  "displayName": "LIS_LIS_QMO_RENEWAL_COMPENSATION",
  "shortName": null,
  "standardName": null,
  "id": 50062153880,
  "availableFlag": 1,
  "dataTypeId": 10000081633,
  "visibleFlag": true,
  "nullableFlag": true,
  "pickListId": 50062153877,
  "displayOrder": null,
  "updatableFlag": true,
  "enterableFlag": true,
  "copyOnCloneFlag": true,
  "isDeprecated": false
}