{
  "configType": "FIELD",
  "description": "Represent a StreetSourceName field",
  "systemName": "StreetSourceName_DN_STR_SOURCE_NAME",
  "displayName": "LIS_ADDR_ADDRESS_TYPES_PROPERTY_",
  "shortName": null,
  "standardName": null,
  "id": 50073871935,
  "availableFlag": 1,
  "dataTypeId": 10094160270,
  "visibleFlag": true,
  "nullableFlag": true,
  "pickListId": null,
  "displayOrder": null,
  "updatableFlag": true,
  "enterableFlag": true,
  "copyOnCloneFlag": true,
  "isDeprecated": false
}