{
  "configType": "FIELD",
  "description": "Represent a TeamMemberModificationTimestamp field",
  "systemName": "TeamMemberModificationTimestamp_MODIFIED_TMS",
  "displayName": "SYS_TMBUI_MODIFIED_TMS",
  "shortName": null,
  "standardName": null,
  "id": 550016246756,
  "availableFlag": 1,
  "dataTypeId": 10000000121,
  "visibleFlag": true,
  "nullableFlag": false,
  "pickListId": null,
  "displayOrder": null,
  "updatableFlag": true,
  "enterableFlag": true,
  "copyOnCloneFlag": true,
  "isDeprecated": false
}