{
  "configType": "FIELD",
  "description": "Represent a MIREXSaleOfficeFullOfficeName field",
  "systemName": "MIREXSaleOfficeFullOfficeName_OfficeName",
  "displayName": "MIREXSaleOfficeFullOfficeName",
  "shortName": null,
  "standardName": "BuyerOfficeName",
  "id": 550016878210,
  "availableFlag": 1,
  "dataTypeId": 50041935181,
  "visibleFlag": true,
  "nullableFlag": true,
  "pickListId": null,
  "displayOrder": null,
  "updatableFlag": true,
  "enterableFlag": true,
  "copyOnCloneFlag": true,
  "isDeprecated": false
}