{
  "configType": "FIELD",
  "description": "Represent a BRIGHTLsubRequestedClassKey field",
  "systemName": "BRIGHTLsubRequestedClassKey_REQUESTED_SC_ID",
  "displayName": "BRIGHTLsubRequestedClassKey",
  "shortName": null,
  "standardName": null,
  "id": 550016842250,
  "availableFlag": 1,
  "dataTypeId": 10000000161,
  "visibleFlag": true,
  "nullableFlag": true,
  "pickListId": 10025709817,
  "displayOrder": null,
  "updatableFlag": true,
  "enterableFlag": true,
  "copyOnCloneFlag": true,
  "isDeprecated": false
}