{
  "configType": "FIELD",
  "description": "Represent a MIREXSemiAnnualTaxAmt field",
  "systemName": "MIREXSemiAnnualTaxAmt_SemiAnnualTaxAmt",
  "displayName": "MIREXSemiAnnualTaxAmt",
  "shortName": null,
  "standardName": null,
  "id": 550016878358,
  "availableFlag": 1,
  "dataTypeId": 10000000148,
  "visibleFlag": true,
  "nullableFlag": true,
  "pickListId": null,
  "displayOrder": null,
  "updatableFlag": true,
  "enterableFlag": true,
  "copyOnCloneFlag": true,
  "isDeprecated": false
}