{
  "configType": "FIELD",
  "description": "Represent a WIREXAgentOfficePhone field",
  "systemName": "WIREXAgentOfficePhone_AgentOfficePhone",
  "displayName": "WIREXAgentOfficePhone",
  "shortName": null,
  "standardName": "MemberOfficePhone",
  "id": 550016720498,
  "availableFlag": 1,
  "dataTypeId": 10000000160,
  "visibleFlag": true,
  "nullableFlag": true,
  "pickListId": null,
  "displayOrder": null,
  "updatableFlag": true,
  "enterableFlag": true,
  "copyOnCloneFlag": true,
  "isDeprecated": false
}