{
  "configType": "FIELD",
  "description": "Represent a MapCoordinateSource field",
  "systemName": "MapCoordinateSource_QSS_MAP_COORDINATE_SOURCE",
  "displayName": "LIS_LIS_QSS_MAP_COORDINATE_SOURC",
  "shortName": null,
  "standardName": "MapCoordinateSource",
  "id": 85011871129,
  "availableFlag": 1,
  "dataTypeId": 10000081639,
  "visibleFlag": true,
  "nullableFlag": true,
  "pickListId": null,
  "displayOrder": null,
  "updatableFlag": true,
  "enterableFlag": true,
  "copyOnCloneFlag": true,
  "isDeprecated": false
}