{
  "configType": "FIELD",
  "description": "Represent a RecRm1Dimenstions field",
  "systemName": "RecRm1Dimenstions_QSS_DIMENSIONS",
  "displayName": "LIS_ROOM_SUB_ROOM_TYPES_RECREATI",
  "shortName": null,
  "standardName": "RoomRecRm1Dimensions",
  "id": 85011876998,
  "availableFlag": 1,
  "dataTypeId": 10000081639,
  "visibleFlag": true,
  "nullableFlag": true,
  "pickListId": null,
  "displayOrder": null,
  "updatableFlag": true,
  "enterableFlag": true,
  "copyOnCloneFlag": true,
  "isDeprecated": false
}